manim/__init__.py
manim/constants.py
manim/typing.py
manim/_config/__init__.py
manim/_config/default.cfg
manim/_config/utils.py
manim/animation/__init__.py
manim/animation/animation.py
manim/animation/changing.py
manim/animation/composition.py
manim/animation/creation.py
manim/animation/fading.py
manim/animation/growing.py
manim/animation/indication.py
manim/animation/movement.py
manim/animation/rotation.py
manim/animation/specialized.py
manim/animation/speedmodifier.py
manim/animation/transform.py
manim/animation/transform_matching_parts.py
manim/animation/updaters/__init__.py
manim/animation/updaters/mobject_update_utils.py
manim/animation/updaters/update.py
manim/camera/__init__.py
manim/camera/camera.py
manim/camera/mapping_camera.py
manim/camera/moving_camera.py
manim/camera/multi_camera.py
manim/camera/three_d_camera.py
manim/mobject/__init__.py
manim/mobject/frame.py
manim/mobject/graph.py
manim/mobject/logo.py
manim/mobject/mobject.py
manim/mobject/table.py
manim/mobject/utils.py
manim/mobject/value_tracker.py
manim/mobject/vector_field.py
manim/mobject/geometry/__init__.py
manim/mobject/geometry/arc.py
manim/mobject/geometry/boolean_ops.py
manim/mobject/geometry/line.py
manim/mobject/geometry/polygram.py
manim/mobject/geometry/shape_matchers.py
manim/mobject/geometry/tips.py
manim/mobject/graphing/__init__.py
manim/mobject/graphing/coordinate_systems.py
manim/mobject/graphing/functions.py
manim/mobject/graphing/number_line.py
manim/mobject/graphing/probability.py
manim/mobject/graphing/scale.py
manim/mobject/opengl/opengl_compatibility.py
manim/mobject/svg/__init__.py
manim/mobject/svg/brace.py
manim/mobject/svg/svg_mobject.py
manim/mobject/text/numbers.py
manim/mobject/text/tex_mobject.py
manim/mobject/three_d/__init__.py
manim/mobject/three_d/three_d_utils.py
manim/mobject/three_d/three_dimensions.py
manim/mobject/types/__init__.py
manim/mobject/types/image_mobject.py
manim/mobject/types/vectorized_mobject.py
manim/plugins/__init__.py
manim_web-0.1.8.post0.dist-info/METADATA
manim_web-0.1.8.post0.dist-info/WHEEL
manim_web-0.1.8.post0.dist-info/entry_points.txt
manim_web-0.1.8.post0.dist-info/licenses/LICENSE
manim_web-0.1.8.post0.dist-info/licenses/LICENSE.community
manim_web-0.1.8.post0.dist-info/RECORD
