Metadata-Version: 2.4
Name: manim-web
Version: 0.1.8.post0
Summary: Animation engine for explanatory math videos, for the web.
Project-URL: repository, https://github.com/MathItYT/manim
Project-URL: documentation, https://docs.manim.community/
Project-URL: homepage, https://www.manim.community/
Project-URL: Bug Tracker, https://github.com/MathItYT/manim/issues
Project-URL: Changelog, https://docs.manim.community/en/stable/changelog.html
Project-URL: Discord, https://www.manim.community/discord/
Author-email: Benjamín Ubilla <benjamin.ubilla@uc.cl>
License-Expression: MIT
License-File: LICENSE
License-File: LICENSE.community
Classifier: Development Status :: 4 - Beta
Classifier: License :: OSI Approved :: MIT License
Classifier: Natural Language :: English
Classifier: Programming Language :: Python :: 3.9
Classifier: Programming Language :: Python :: 3.10
Classifier: Programming Language :: Python :: 3.11
Classifier: Programming Language :: Python :: 3.12
Classifier: Programming Language :: Python :: 3.13
Classifier: Topic :: Multimedia :: Graphics
Classifier: Topic :: Multimedia :: Video
Classifier: Topic :: Scientific/Engineering
Requires-Python: >=3.9
Requires-Dist: audioop-lts>=0.2.1; python_full_version >= '3.13'
Requires-Dist: beautifulsoup4>=4.12
Requires-Dist: decorator>=4.3.2
Requires-Dist: importlib-metadata>=8.6.1; python_full_version < '3.10'
Requires-Dist: isosurfaces>=0.1.0
Requires-Dist: networkx>=2.6
Requires-Dist: numpy<=2.2.5
Requires-Dist: pillow>=9.1
Requires-Dist: pygments>=2.0.0
Requires-Dist: scipy>=1.13.0
Requires-Dist: scipy>=1.14.0; python_full_version >= '3.13'
Requires-Dist: svgelements>=1.8.0
Requires-Dist: typing-extensions>=4.12.0
